ct/__init__.py
ct/timing.py
cool_testing-0.2.dist-info/LICENSE
cool_testing-0.2.dist-info/METADATA
cool_testing-0.2.dist-info/WHEEL
cool_testing-0.2.dist-info/top_level.txt
cool_testing-0.2.dist-info/RECORD
