Metadata-Version: 2.1
Name: cool-testing
Version: 0.2
License-File: LICENSE
